python_helpers/__init__.py
python_helpers/cli.py
python_helpers/python_helpers.py
python_helpers-0.3.0.dist-info/AUTHORS.rst
python_helpers-0.3.0.dist-info/LICENSE
python_helpers-0.3.0.dist-info/METADATA
python_helpers-0.3.0.dist-info/WHEEL
python_helpers-0.3.0.dist-info/entry_points.txt
python_helpers-0.3.0.dist-info/top_level.txt
python_helpers-0.3.0.dist-info/RECORD
