Metadata-Version: 1.1
Name: python-helpers
Version: 0.3.0
Summary: Python Helpers contains reusable functions for routine automation.
Home-page: https://github.com/and1er/python_helpers
Author: Andrei Losenkov
Author-email: w.alosenkov@gmail.com
License: MIT license
Keywords: python_helpers
Platform: UNKNOWN
Classifier: Development Status :: 2 - Pre-Alpha
Classifier: Intended Audience :: Developers
Classifier: License :: OSI Approved :: MIT License
Classifier: Natural Language :: English
Classifier: Programming Language :: Python :: 2
Classifier: Programming Language :: Python :: 2.7
Classifier: Programming Language :: Python :: 3
Classifier: Programming Language :: Python :: 3.4
Classifier: Programming Language :: Python :: 3.5
Classifier: Programming Language :: Python :: 3.6
Classifier: Programming Language :: Python :: 3.7
